merlin_interface/__init__.py
merlin_interface/conftest.py
merlin_interface/merlin_interface.py
merlin_interface/testing_tools.py
merlin_interface/tests/__init__.py
merlin_interface/tests/test_merlin_interface_class.py
merlin_interface/tests/test_testing_tools.py
merlin_interface-0.0.6.dist-info/LICENSE
merlin_interface-0.0.6.dist-info/METADATA
merlin_interface-0.0.6.dist-info/WHEEL
merlin_interface-0.0.6.dist-info/top_level.txt
merlin_interface-0.0.6.dist-info/RECORD
