Metadata-Version: 2.1
Name: merlin_interface
Version: 0.0.6
Summary: Library for interfacing with the Merlin Medipix3 readout software over the TCP/IP API
Author-email: Magnus Nord <magnunor@gmail.com>
License: GNU LESSER GENERAL PUBLIC LICENSE
Project-URL: Homepage, https://fast_pixelated_detectors.gitlab.io/merlin_interface/
Project-URL: Documentation, https://fast_pixelated_detectors.gitlab.io/merlin_interface/tutorial
Project-URL: Repository, https://gitlab.com/fast_pixelated_detectors/merlin_interface
Project-URL: Issues, https://gitlab.com/fast_pixelated_detectors/merlin_interface/-/issues
Keywords: TPC/IP,interface,Merlin,Medipix3,microscopy
Classifier: Development Status :: 3 - Alpha
Classifier: Intended Audience :: Science/Research
Classifier: Programming Language :: Python :: 3
License-File: LICENSE
